chilitools/__init__.py
chilitools/api/__init__.py
chilitools/api/connector.py
chilitools/api/endpoints.py
chilitools/api/mycp.py
chilitools/api/response.py
chilitools/grafx/__init__.py
chilitools/grafx/api/__init__.py
chilitools/grafx/api/environment.py
chilitools/grafx/api/platform.py
chilitools/grafx/auth.py
chilitools/grafx/connector.py
chilitools/grafx/document.py
chilitools/grafx/environment.py
chilitools/publisher/__init__.py
chilitools/publisher/document.py
chilitools/settings/__init__.py
chilitools/settings/config.py
chilitools/utilities/ServerMigration.py
chilitools/utilities/__init__.py
chilitools/utilities/backoffice.py
chilitools/utilities/defaults.py
chilitools/utilities/document.py
chilitools/utilities/errors.py
chilitools/utilities/file.py
chilitools/utilities/logger.py
chilitools/utilities/strings.py
chilitools/utilities/xmltools.py
chilitools-0.2.8.dist-info/METADATA
chilitools-0.2.8.dist-info/WHEEL
chilitools-0.2.8.dist-info/RECORD
