Metadata-Version: 2.1
Name: chilitools
Version: 0.2.8
Summary: A collection of tools for working with CHILI products
Author: Austin
Author-email: austin.meier@hotmail.com
Requires-Python: >=3.9,<4.0
Classifier: Programming Language :: Python :: 3
Classifier: Programming Language :: Python :: 3.9
Classifier: Programming Language :: Python :: 3.10
Classifier: Programming Language :: Python :: 3.11
Requires-Dist: beautifulsoup4 (>=4.11.1,<5.0.0)
Requires-Dist: coloredlogs (>=15.0.1,<16.0.0)
Requires-Dist: lxml (>=4.9.2,<5.0.0)
Requires-Dist: packaging (>=21.3,<22.0)
Requires-Dist: pyperclip (>=1.8.2,<2.0.0)
Requires-Dist: requests (>=2.27.1,<3.0.0)
Requires-Dist: xmltodict (>=0.12.0,<0.13.0)
